runtime/reflection/lite/__init__.py
runtime/reflection/lite/core/__init__.py
runtime/reflection/lite/core/attributes.py
runtime/reflection/lite/core/cache.py
runtime/reflection/lite/core/helpers.py
runtime/reflection/lite/core/misc.py
runtime/reflection/lite/core/resolving.py
runtime/reflection/lite/core/threading.py
runtime/reflection/lite/core/types.py
runtime/reflection/lite/core/objects/access_mode.py
runtime/reflection/lite/core/objects/class_.py
runtime/reflection/lite/core/objects/constructor.py
runtime/reflection/lite/core/objects/deferred_reflection.py
runtime/reflection/lite/core/objects/delegate.py
runtime/reflection/lite/core/objects/field.py
runtime/reflection/lite/core/objects/function.py
runtime/reflection/lite/core/objects/function_kind.py
runtime/reflection/lite/core/objects/member.py
runtime/reflection/lite/core/objects/member_collection.py
runtime/reflection/lite/core/objects/member_filter.py
runtime/reflection/lite/core/objects/member_info.py
runtime/reflection/lite/core/objects/member_type.py
runtime/reflection/lite/core/objects/method.py
runtime/reflection/lite/core/objects/module.py
runtime/reflection/lite/core/objects/parameter.py
runtime/reflection/lite/core/objects/parameter_kind.py
runtime/reflection/lite/core/objects/parameter_mapper.py
runtime/reflection/lite/core/objects/property_.py
runtime/reflection/lite/core/objects/signature.py
runtime/reflection/lite/core/objects/undefined.py
runtime/reflection/lite/core/objects/variable.py
runtime_reflection_lite-0.1.2.dist-info/licenses/LICENSE
runtime_reflection_lite-0.1.2.dist-info/METADATA
runtime_reflection_lite-0.1.2.dist-info/WHEEL
runtime_reflection_lite-0.1.2.dist-info/top_level.txt
runtime_reflection_lite-0.1.2.dist-info/RECORD
