Metadata-Version: 2.4
Name: runtime-reflection-lite
Version: 0.1.2
Summary: Runtime reflection (lite)
Author-email: Anders Madsen <anders.madsen@alphavue.com>
License-Expression: MIT
Project-URL: repository, https://github.com/apmadsen/runtime-reflection-lite
Keywords: windows,linux,async,reflection,inspection
Classifier: Development Status :: 5 - Production/Stable
Classifier: Development Status :: 6 - Mature
Classifier: Operating System :: Microsoft :: Windows
Classifier: Operating System :: POSIX :: Linux
Classifier: Intended Audience :: Developers
Classifier: Natural Language :: English
Classifier: Programming Language :: Python :: 3 :: Only
Classifier: Programming Language :: Python :: 3
Classifier: Programming Language :: Python :: 3.10
Classifier: Programming Language :: Python :: 3.11
Classifier: Programming Language :: Python :: 3.12
Classifier: Programming Language :: Python :: 3.13
Classifier: Programming Language :: Python
Classifier: Topic :: Software Development :: Libraries :: Python Modules
Classifier: Topic :: Software Development :: Libraries
Classifier: Typing :: Typed
Requires-Python: >=3.10
License-File: LICENSE
Requires-Dist: typing-utilities<0.2,>=0.1.0
Requires-Dist: deprecated<1.3,>=1.2
Provides-Extra: test
Requires-Dist: pytest>=8.3; extra == "test"
Requires-Dist: pytest-cov>=6.1; extra == "test"
Dynamic: license-file
